configy/__init__.py
configy/config_container.py
configy/helpers.py
configy/py.typed
configy/testconfig.py
configy-0.2.0.dist-info/licenses/LICENSE
configy-0.2.0.dist-info/METADATA
configy-0.2.0.dist-info/WHEEL
configy-0.2.0.dist-info/top_level.txt
configy-0.2.0.dist-info/RECORD
