Metadata-Version: 2.4
Name: configy
Version: 0.2.0
Summary: Simple Configuration manager, plays well with testing
Author-email: Nickolas Grigoriadis <nagrigoriadis@proton.me>
License-Expression: MIT
Project-URL: Repository, https://codeberg.org/grigi/configy
Classifier: Development Status :: 5 - Production/Stable
Classifier: Intended Audience :: Developers
Classifier: Operating System :: OS Independent
Classifier: Programming Language :: Python
Classifier: Programming Language :: Python :: 3.8
Classifier: Programming Language :: Python :: 3.9
Classifier: Programming Language :: Python :: 3.10
Classifier: Programming Language :: Python :: 3.11
Classifier: Programming Language :: Python :: 3.12
Classifier: Programming Language :: Python :: 3.13
Classifier: Programming Language :: Python :: 3.14
Classifier: Topic :: Software Development :: Libraries :: Python Modules
Requires-Python: >=3.8
License-File: LICENSE
Requires-Dist: PyYAML>=6.0.2
Dynamic: license-file
